comfyapi/__init__.py
comfyapi/client.py
comfyapi-2.0.1.dist-info/licenses/LICENSE
comfyapi-2.0.1.dist-info/METADATA
comfyapi-2.0.1.dist-info/WHEEL
comfyapi-2.0.1.dist-info/top_level.txt
comfyapi-2.0.1.dist-info/RECORD
