Metadata-Version: 2.4
Name: comfyapi
Version: 2.0.1
Summary: A Python client library for interacting with the ComfyUI API.
Home-page: https://github.com/samratbarai/comfyapi-client
Author: Samrat
Author-email: baraisamrat20@gmail.com
Classifier: Programming Language :: Python :: 3
Classifier: Operating System :: OS Independent
Requires-Python: >=3.7
License-File: LICENSE
Requires-Dist: requests>=2.20.0
Requires-Dist: websocket-client>=1.0.0
Dynamic: author
Dynamic: author-email
Dynamic: classifier
Dynamic: description
Dynamic: description-content-type
Dynamic: home-page
Dynamic: license-file
Dynamic: requires-dist
Dynamic: requires-python
Dynamic: summary
